{
  "CRGY": {
    "close": 11.845,
    "ema_9": 11.8595,
    "ema_21": 11.862,
    "rsi": 41.9229,
    "macd": -0.0001,
    "macd_signal": 0.0034,
    "macd_hist": -0.0035,
    "atr": 0.0095,
    "vwap": 11.808,
    "rel_vol": 1.0664,
    "macd_hist_rising": false,
    "symbol": "CRGY",
    "avg_volume_20d": 435314.0,
    "ema_200_daily": 10.9548,
    "atr_pct": 0.08
  },
  "HGV": {
    "close": 49.5,
    "ema_9": 49.7064,
    "ema_21": 49.9418,
    "rsi": 25.4212,
    "macd": -0.2076,
    "macd_signal": -0.1372,
    "macd_hist": -0.0704,
    "atr": 0.082,
    "vwap": 50.1866,
    "rel_vol": 0.3892,
    "macd_hist_rising": false,
    "symbol": "HGV",
    "avg_volume_20d": 63082.0,
    "ema_200_daily": 46.1081,
    "atr_pct": 0.166
  },
  "DEC": {
    "close": 14.27,
    "ema_9": 14.272,
    "ema_21": 14.2825,
    "rsi": 45.7836,
    "macd": -0.0143,
    "macd_signal": -0.0183,
    "macd_hist": 0.004,
    "atr": 0.0189,
    "vwap": 14.3196,
    "rel_vol": 0.7353,
    "macd_hist_rising": false,
    "symbol": "DEC",
    "avg_volume_20d": 35423.0,
    "ema_200_daily": 14.9496,
    "atr_pct": 0.132
  },
  "MPC": {
    "close": 266.63,
    "ema_9": 266.6296,
    "ema_21": 266.7449,
    "rsi": 47.1907,
    "macd": -0.082,
    "macd_signal": -0.0231,
    "macd_hist": -0.0589,
    "atr": 0.1817,
    "vwap": 266.6051,
    "rel_vol": 0.7958,
    "macd_hist_rising": false,
    "symbol": "MPC",
    "avg_volume_20d": 107281.0,
    "ema_200_daily": 213.4325,
    "atr_pct": 0.068
  }
}