{
  "generated_at": "2026-06-11T12:36:12.008139+00:00",
  "results": {
    "NVDA": {
      "symbol": "NVDA",
      "sentiment": "positive",
      "summary": "Nvidia remains a large-cap momentum name, and recent market commentary highlights continued analyst attention and strong relative performance into June. [4]",
      "key_points": [
        "Nvidia remains a large-cap momentum name, and recent market commentary highlights continued analyst attention and strong relative performance into June. [4]"
      ],
      "error": null
    },
    "META": {
      "symbol": "META",
      "sentiment": "positive",
      "summary": "Meta is a high-liquidity mega-cap with ongoing positive sentiment, and recent June commentary described it as a core position being actively added to. [5]",
      "key_points": [
        "Meta is a high-liquidity mega-cap with ongoing positive sentiment, and recent June commentary described it as a core position being actively added to. [5]"
      ],
      "error": null
    },
    "MA": {
      "symbol": "MA",
      "sentiment": "positive",
      "summary": "Mastercard is a steady large-cap compounder that continues to screen as a quality momentum name in broad market lists. [5]",
      "key_points": [
        "Mastercard is a steady large-cap compounder that continues to screen as a quality momentum name in broad market lists. [5]"
      ],
      "error": null
    },
    "NU": {
      "symbol": "NU",
      "sentiment": "positive",
      "summary": "Nu Holdings has been cited in June buying commentary as a strong-growth fintech name with continued revenue and earnings expansion. [5]",
      "key_points": [
        "Nu Holdings has been cited in June buying commentary as a strong-growth fintech name with continued revenue and earnings expansion. [5]"
      ],
      "error": null
    },
    "MELI": {
      "symbol": "MELI",
      "sentiment": "positive",
      "summary": "MercadoLibre remains a high-momentum Latin American e-commerce/fintech leader favored in June portfolio discussions. [5]",
      "key_points": [
        "MercadoLibre remains a high-momentum Latin American e-commerce/fintech leader favored in June portfolio discussions. [5]"
      ],
      "error": null
    },
    "LMB": {
      "symbol": "LMB",
      "sentiment": "positive",
      "summary": "Limbach has been highlighted in June as an interesting stock pick with positive business momentum. [5]",
      "key_points": [
        "Limbach has been highlighted in June as an interesting stock pick with positive business momentum. [5]"
      ],
      "error": null
    },
    "HGV": {
      "symbol": "HGV",
      "sentiment": "positive",
      "summary": "Hilton Grand Vacations appears on Zacks\u2019 June 2026 \u201cbest stocks to buy now\u201d list, supported by recent positive price action. [2]",
      "key_points": [
        "Hilton Grand Vacations appears on Zacks\u2019 June 2026 \u201cbest stocks to buy now\u201d list, supported by recent positive price action. [2]"
      ],
      "error": null
    },
    "MPC": {
      "symbol": "MPC",
      "sentiment": "positive",
      "summary": "Marathon Petroleum appears on Zacks\u2019 June 2026 \u201cbest stocks to buy now\u201d list and has shown solid recent strength. [2]",
      "key_points": [
        "Marathon Petroleum appears on Zacks\u2019 June 2026 \u201cbest stocks to buy now\u201d list and has shown solid recent strength. [2]"
      ],
      "error": null
    },
    "CRGY": {
      "symbol": "CRGY",
      "sentiment": "positive",
      "summary": "Crescent Energy appears on Zacks\u2019 June 2026 \u201cbest stocks to buy now\u201d list as a lower-valuation energy name with growth appeal. [2]",
      "key_points": [
        "Crescent Energy appears on Zacks\u2019 June 2026 \u201cbest stocks to buy now\u201d list as a lower-valuation energy name with growth appeal. [2]"
      ],
      "error": null
    },
    "DEC": {
      "symbol": "DEC",
      "sentiment": "positive",
      "summary": "Diversified Energy appears on Zacks\u2019 June 2026 \u201cbest stocks to buy now\u201d list as a value-oriented energy stock. [2]",
      "key_points": [
        "Diversified Energy appears on Zacks\u2019 June 2026 \u201cbest stocks to buy now\u201d list as a value-oriented energy stock. [2]"
      ],
      "error": null
    },
    "LNVGY": {
      "symbol": "LNVGY",
      "sentiment": "positive",
      "summary": "Lenovo Group is listed by Zacks as a top June 2026 stock pick with very strong 12-week price performance. [2]",
      "key_points": [
        "Lenovo Group is listed by Zacks as a top June 2026 stock pick with very strong 12-week price performance. [2]"
      ],
      "error": null
    },
    "SNDK": {
      "symbol": "SNDK",
      "sentiment": "positive",
      "summary": "Sandisk is one of the strongest-performing S&P 500 names in 2026, reflecting powerful relative strength. [3]",
      "key_points": [
        "Sandisk is one of the strongest-performing S&P 500 names in 2026, reflecting powerful relative strength. [3]"
      ],
      "error": null
    },
    "TPL": {
      "symbol": "TPL",
      "sentiment": "positive",
      "summary": "Texas Pacific Land has posted major year-to-date gains in 2026 and remains a strong momentum stock. [3]",
      "key_points": [
        "Texas Pacific Land has posted major year-to-date gains in 2026 and remains a strong momentum stock. [3]"
      ],
      "error": null
    },
    "MRNA": {
      "symbol": "MRNA",
      "sentiment": "positive",
      "summary": "Moderna has been one of the top S&P 500 performers in 2026, indicating strong price momentum. [3]",
      "key_points": [
        "Moderna has been one of the top S&P 500 performers in 2026, indicating strong price momentum. [3]"
      ],
      "error": null
    },
    "GNRC": {
      "symbol": "GNRC",
      "sentiment": "positive",
      "summary": "Generac has delivered strong 2026 returns and fits the large-cap momentum profile. [3]",
      "key_points": [
        "Generac has delivered strong 2026 returns and fits the large-cap momentum profile. [3]"
      ],
      "error": null
    },
    "GLW": {
      "symbol": "GLW",
      "sentiment": "positive",
      "summary": "Corning is among 2026\u2019s best-performing S&P 500 stocks and remains in a strong uptrend. [3]",
      "key_points": [
        "Corning is among 2026\u2019s best-performing S&P 500 stocks and remains in a strong uptrend. [3]"
      ],
      "error": null
    },
    "TER": {
      "symbol": "TER",
      "sentiment": "positive",
      "summary": "Teradyne has been one of the top S&P 500 performers in 2026, signaling robust relative strength. [3]",
      "key_points": [
        "Teradyne has been one of the top S&P 500 performers in 2026, signaling robust relative strength. [3]"
      ],
      "error": null
    },
    "WDC": {
      "symbol": "WDC",
      "sentiment": "positive",
      "summary": "Western Digital has posted strong 2026 gains and continues to show momentum. [3]",
      "key_points": [
        "Western Digital has posted strong 2026 gains and continues to show momentum. [3]"
      ],
      "error": null
    },
    "FIX": {
      "symbol": "FIX",
      "sentiment": "positive",
      "summary": "Comfort Systems USA has been a standout 2026 winner with strong price performance. [3]",
      "key_points": [
        "Comfort Systems USA has been a standout 2026 winner with strong price performance. [3]"
      ],
      "error": null
    },
    "STX": {
      "symbol": "STX",
      "sentiment": "positive",
      "summary": "Seagate Technology is another strong 2026 performer in the data-storage group. [3]",
      "key_points": [
        "Seagate Technology is another strong 2026 performer in the data-storage group. [3]"
      ],
      "error": null
    },
    "CIEN": {
      "symbol": "CIEN",
      "sentiment": "positive",
      "summary": "Ciena has delivered powerful 2026 gains and continues to screen as a strong momentum stock. [3]",
      "key_points": [
        "Ciena has delivered powerful 2026 gains and continues to screen as a strong momentum stock. [3]"
      ],
      "error": null
    },
    "ANET": {
      "symbol": "ANET",
      "sentiment": "positive",
      "summary": "Arista Networks has shown strong one-year relative strength and remains a favored large-cap networking name. [6]",
      "key_points": [
        "Arista Networks has shown strong one-year relative strength and remains a favored large-cap networking name. [6]"
      ],
      "error": null
    },
    "WYNN": {
      "symbol": "WYNN",
      "sentiment": "positive",
      "summary": "Wynn Resorts has appeared among strong one-year performers, reflecting recent momentum. [6]",
      "key_points": [
        "Wynn Resorts has appeared among strong one-year performers, reflecting recent momentum. [6]"
      ],
      "error": null
    },
    "NWSA": {
      "symbol": "NWSA",
      "sentiment": "positive",
      "summary": "News Corp has shown positive one-year performance and remains in a constructive trend. [6]",
      "key_points": [
        "News Corp has shown positive one-year performance and remains in a constructive trend. [6]"
      ],
      "error": null
    },
    "SW": {
      "symbol": "SW",
      "sentiment": "positive",
      "summary": "Smurfit WestRock has posted positive one-year returns and fits the relative-strength screen. [6]",
      "key_points": [
        "Smurfit WestRock has posted positive one-year returns and fits the relative-strength screen. [6]"
      ],
      "error": null
    }
  }
}